photon_lang/__init__.py
photon_lang-0.0.1.dist-info/LICENSE
photon_lang-0.0.1.dist-info/METADATA
photon_lang-0.0.1.dist-info/WHEEL
photon_lang-0.0.1.dist-info/top_level.txt
photon_lang-0.0.1.dist-info/RECORD
