Metadata-Version: 2.1
Name: photon-lang
Version: 0.0.1
Summary: Import Photon libraries in Python
Home-page: https://github.com/HashLDash/photon-lang
Author: HashLDash
Author-email: digameoquepensas@gmail.com
License: UNKNOWN
Project-URL: Bug Tracker, https://github.com/HashLDash/photon-lang/issues
Platform: UNKNOWN
Classifier: Programming Language :: Python :: 3
Classifier: License :: OSI Approved :: MIT License
Classifier: Operating System :: OS Independent
Requires-Python: >=3.6
License-File: LICENSE
